{
  "papi_version":"7.0.1.0",
  "cpu_info":"AMD EPYC 7H12 64-Core Processor",
  "max_cpu_rate_mhz":"2600",
  "min_cpu_rate_mhz":"1500",
  "event_definitions":{
    "PAPI_L2_DCM":{
      "component":"perf_event",
      "type":"delta"
    }
  },
  "threads":{
    "0":{
      "regions":{
        "0":{
          "name":"v0",
          "parent_region_id":"-1",
          "cycles":"394531800",
          "real_time_nsec":"152018503",
          "PAPI_L2_DCM":"500186"
        },
        "1":{
          "name":"isend",
          "parent_region_id":"-1",
          "cycles":"71972576",
          "real_time_nsec":"27730808",
          "PAPI_L2_DCM":"14243"
        },
        "2":{
          "name":"onesided",
          "parent_region_id":"-1",
          "cycles":"125639800",
          "real_time_nsec":"48408077",
          "PAPI_L2_DCM":"43744"
        },
        "3":{
          "name":"bcast",
          "parent_region_id":"-1",
          "cycles":"54938494",
          "real_time_nsec":"21166367",
          "PAPI_L2_DCM":"251665"
        },
        "4":{
          "name":"v0",
          "parent_region_id":"-1",
          "cycles":"348964954",
          "real_time_nsec":"134468273",
          "PAPI_L2_DCM":"475137"
        },
        "5":{
          "name":"isend",
          "parent_region_id":"-1",
          "cycles":"61675354",
          "real_time_nsec":"23762500",
          "PAPI_L2_DCM":"15471"
        },
        "6":{
          "name":"onesided",
          "parent_region_id":"-1",
          "cycles":"110197074",
          "real_time_nsec":"42460425",
          "PAPI_L2_DCM":"28864"
        },
        "7":{
          "name":"bcast",
          "parent_region_id":"-1",
          "cycles":"56307316",
          "real_time_nsec":"21694428",
          "PAPI_L2_DCM":"259162"
        },
        "8":{
          "name":"v0",
          "parent_region_id":"-1",
          "cycles":"357361238",
          "real_time_nsec":"137702093",
          "PAPI_L2_DCM":"475407"
        },
        "9":{
          "name":"isend",
          "parent_region_id":"-1",
          "cycles":"60634444",
          "real_time_nsec":"23359403",
          "PAPI_L2_DCM":"13900"
        },
        "10":{
          "name":"onesided",
          "parent_region_id":"-1",
          "cycles":"104595582",
          "real_time_nsec":"40300811",
          "PAPI_L2_DCM":"29864"
        },
        "11":{
          "name":"bcast",
          "parent_region_id":"-1",
          "cycles":"54426398",
          "real_time_nsec":"20969949",
          "PAPI_L2_DCM":"263375"
        },
        "12":{
          "name":"v0",
          "parent_region_id":"-1",
          "cycles":"350848628",
          "real_time_nsec":"135194338",
          "PAPI_L2_DCM":"509012"
        },
        "13":{
          "name":"isend",
          "parent_region_id":"-1",
          "cycles":"61486620",
          "real_time_nsec":"23691477",
          "PAPI_L2_DCM":"13823"
        },
        "14":{
          "name":"onesided",
          "parent_region_id":"-1",
          "cycles":"103328628",
          "real_time_nsec":"39814368",
          "PAPI_L2_DCM":"29531"
        },
        "15":{
          "name":"bcast",
          "parent_region_id":"-1",
          "cycles":"56744350",
          "real_time_nsec":"21861633",
          "PAPI_L2_DCM":"255377"
        },
        "16":{
          "name":"v0",
          "parent_region_id":"-1",
          "cycles":"365611870",
          "real_time_nsec":"140875572",
          "PAPI_L2_DCM":"470352"
        },
        "17":{
          "name":"isend",
          "parent_region_id":"-1",
          "cycles":"61476870",
          "real_time_nsec":"23686928",
          "PAPI_L2_DCM":"18244"
        },
        "18":{
          "name":"onesided",
          "parent_region_id":"-1",
          "cycles":"100985482",
          "real_time_nsec":"38907897",
          "PAPI_L2_DCM":"36355"
        },
        "19":{
          "name":"bcast",
          "parent_region_id":"-1",
          "cycles":"72689656",
          "real_time_nsec":"28007298",
          "PAPI_L2_DCM":"262348"
        },
        "20":{
          "name":"v0",
          "parent_region_id":"-1",
          "cycles":"359596094",
          "real_time_nsec":"138557061",
          "PAPI_L2_DCM":"478677"
        },
        "21":{
          "name":"isend",
          "parent_region_id":"-1",
          "cycles":"62776558",
          "real_time_nsec":"24188700",
          "PAPI_L2_DCM":"17173"
        },
        "22":{
          "name":"onesided",
          "parent_region_id":"-1",
          "cycles":"101317268",
          "real_time_nsec":"39040335",
          "PAPI_L2_DCM":"29396"
        },
        "23":{
          "name":"bcast",
          "parent_region_id":"-1",
          "cycles":"61515662",
          "real_time_nsec":"23701997",
          "PAPI_L2_DCM":"253155"
        },
        "24":{
          "name":"v0",
          "parent_region_id":"-1",
          "cycles":"365222884",
          "real_time_nsec":"140732024",
          "PAPI_L2_DCM":"475370"
        },
        "25":{
          "name":"isend",
          "parent_region_id":"-1",
          "cycles":"87288266",
          "real_time_nsec":"33626545",
          "PAPI_L2_DCM":"18331"
        },
        "26":{
          "name":"onesided",
          "parent_region_id":"-1",
          "cycles":"107593902",
          "real_time_nsec":"41458935",
          "PAPI_L2_DCM":"37105"
        },
        "27":{
          "name":"bcast",
          "parent_region_id":"-1",
          "cycles":"60401562",
          "real_time_nsec":"23272851",
          "PAPI_L2_DCM":"258391"
        },
        "28":{
          "name":"v0",
          "parent_region_id":"-1",
          "cycles":"355650438",
          "real_time_nsec":"137037300",
          "PAPI_L2_DCM":"494081"
        },
        "29":{
          "name":"isend",
          "parent_region_id":"-1",
          "cycles":"62347480",
          "real_time_nsec":"24023060",
          "PAPI_L2_DCM":"19080"
        },
        "30":{
          "name":"onesided",
          "parent_region_id":"-1",
          "cycles":"99897018",
          "real_time_nsec":"38490764",
          "PAPI_L2_DCM":"32133"
        },
        "31":{
          "name":"bcast",
          "parent_region_id":"-1",
          "cycles":"57191186",
          "real_time_nsec":"22036091",
          "PAPI_L2_DCM":"265126"
        },
        "32":{
          "name":"v0",
          "parent_region_id":"-1",
          "cycles":"357484894",
          "real_time_nsec":"137747313",
          "PAPI_L2_DCM":"473474"
        },
        "33":{
          "name":"isend",
          "parent_region_id":"-1",
          "cycles":"62095852",
          "real_time_nsec":"23925417",
          "PAPI_L2_DCM":"15243"
        },
        "34":{
          "name":"onesided",
          "parent_region_id":"-1",
          "cycles":"98743294",
          "real_time_nsec":"38049166",
          "PAPI_L2_DCM":"29362"
        },
        "35":{
          "name":"bcast",
          "parent_region_id":"-1",
          "cycles":"56932330",
          "real_time_nsec":"21935372",
          "PAPI_L2_DCM":"260105"
        },
        "36":{
          "name":"v0",
          "parent_region_id":"-1",
          "cycles":"373133488",
          "real_time_nsec":"143780678",
          "PAPI_L2_DCM":"470209"
        },
        "37":{
          "name":"isend",
          "parent_region_id":"-1",
          "cycles":"63059386",
          "real_time_nsec":"24296323",
          "PAPI_L2_DCM":"17801"
        },
        "38":{
          "name":"onesided",
          "parent_region_id":"-1",
          "cycles":"99706906",
          "real_time_nsec":"38418970",
          "PAPI_L2_DCM":"35039"
        },
        "39":{
          "name":"bcast",
          "parent_region_id":"-1",
          "cycles":"59503990",
          "real_time_nsec":"22925339",
          "PAPI_L2_DCM":"259562"
        },
        "40":{
          "name":"v0",
          "parent_region_id":"-1",
          "cycles":"376191582",
          "real_time_nsec":"144959651",
          "PAPI_L2_DCM":"475929"
        },
        "41":{
          "name":"isend",
          "parent_region_id":"-1",
          "cycles":"61290242",
          "real_time_nsec":"23615355",
          "PAPI_L2_DCM":"16333"
        },
        "42":{
          "name":"onesided",
          "parent_region_id":"-1",
          "cycles":"102166142",
          "real_time_nsec":"39366358",
          "PAPI_L2_DCM":"30140"
        },
        "43":{
          "name":"bcast",
          "parent_region_id":"-1",
          "cycles":"57366374",
          "real_time_nsec":"22101122",
          "PAPI_L2_DCM":"262423"
        },
        "44":{
          "name":"v0",
          "parent_region_id":"-1",
          "cycles":"366965144",
          "real_time_nsec":"141404289",
          "PAPI_L2_DCM":"485866"
        },
        "45":{
          "name":"isend",
          "parent_region_id":"-1",
          "cycles":"64692732",
          "real_time_nsec":"24921797",
          "PAPI_L2_DCM":"14946"
        },
        "46":{
          "name":"onesided",
          "parent_region_id":"-1",
          "cycles":"101099206",
          "real_time_nsec":"38953033",
          "PAPI_L2_DCM":"34449"
        },
        "47":{
          "name":"bcast",
          "parent_region_id":"-1",
          "cycles":"66300078",
          "real_time_nsec":"25545137",
          "PAPI_L2_DCM":"261155"
        },
        "48":{
          "name":"v0",
          "parent_region_id":"-1",
          "cycles":"376489360",
          "real_time_nsec":"145073516",
          "PAPI_L2_DCM":"494883"
        },
        "49":{
          "name":"isend",
          "parent_region_id":"-1",
          "cycles":"63825476",
          "real_time_nsec":"24589874",
          "PAPI_L2_DCM":"14265"
        },
        "50":{
          "name":"onesided",
          "parent_region_id":"-1",
          "cycles":"116910222",
          "real_time_nsec":"45041711",
          "PAPI_L2_DCM":"40488"
        },
        "51":{
          "name":"bcast",
          "parent_region_id":"-1",
          "cycles":"93075606",
          "real_time_nsec":"35859547",
          "PAPI_L2_DCM":"276281"
        },
        "52":{
          "name":"v0",
          "parent_region_id":"-1",
          "cycles":"527964268",
          "real_time_nsec":"203432865",
          "PAPI_L2_DCM":"498188"
        },
        "53":{
          "name":"isend",
          "parent_region_id":"-1",
          "cycles":"89091366",
          "real_time_nsec":"34318514",
          "PAPI_L2_DCM":"17715"
        },
        "54":{
          "name":"onesided",
          "parent_region_id":"-1",
          "cycles":"118966848",
          "real_time_nsec":"45841192",
          "PAPI_L2_DCM":"36621"
        },
        "55":{
          "name":"bcast",
          "parent_region_id":"-1",
          "cycles":"101341864",
          "real_time_nsec":"39047140",
          "PAPI_L2_DCM":"261363"
        },
        "56":{
          "name":"v0",
          "parent_region_id":"-1",
          "cycles":"555735674",
          "real_time_nsec":"214135425",
          "PAPI_L2_DCM":"485528"
        },
        "57":{
          "name":"isend",
          "parent_region_id":"-1",
          "cycles":"93205346",
          "real_time_nsec":"35909552",
          "PAPI_L2_DCM":"17317"
        },
        "58":{
          "name":"onesided",
          "parent_region_id":"-1",
          "cycles":"123358274",
          "real_time_nsec":"47522769",
          "PAPI_L2_DCM":"38437"
        },
        "59":{
          "name":"bcast",
          "parent_region_id":"-1",
          "cycles":"54569684",
          "real_time_nsec":"21023912",
          "PAPI_L2_DCM":"263207"
        },
        "60":{
          "name":"v0",
          "parent_region_id":"-1",
          "cycles":"348764234",
          "real_time_nsec":"134389876",
          "PAPI_L2_DCM":"475800"
        },
        "61":{
          "name":"isend",
          "parent_region_id":"-1",
          "cycles":"61174646",
          "real_time_nsec":"23568037",
          "PAPI_L2_DCM":"17979"
        },
        "62":{
          "name":"onesided",
          "parent_region_id":"-1",
          "cycles":"105459848",
          "real_time_nsec":"40621706",
          "PAPI_L2_DCM":"31948"
        },
        "63":{
          "name":"bcast",
          "parent_region_id":"-1",
          "cycles":"58821126",
          "real_time_nsec":"22663138",
          "PAPI_L2_DCM":"262401"
        },
        "64":{
          "name":"v0",
          "parent_region_id":"-1",
          "cycles":"360030346",
          "real_time_nsec":"138732128",
          "PAPI_L2_DCM":"479192"
        },
        "65":{
          "name":"isend",
          "parent_region_id":"-1",
          "cycles":"63468600",
          "real_time_nsec":"24451555",
          "PAPI_L2_DCM":"16785"
        },
        "66":{
          "name":"onesided",
          "parent_region_id":"-1",
          "cycles":"102266398",
          "real_time_nsec":"39399522",
          "PAPI_L2_DCM":"33776"
        },
        "67":{
          "name":"bcast",
          "parent_region_id":"-1",
          "cycles":"67593162",
          "real_time_nsec":"26042842",
          "PAPI_L2_DCM":"256877"
        },
        "68":{
          "name":"v0",
          "parent_region_id":"-1",
          "cycles":"406753464",
          "real_time_nsec":"156736903",
          "PAPI_L2_DCM":"498461"
        },
        "69":{
          "name":"isend",
          "parent_region_id":"-1",
          "cycles":"62008830",
          "real_time_nsec":"23892115",
          "PAPI_L2_DCM":"16356"
        },
        "70":{
          "name":"onesided",
          "parent_region_id":"-1",
          "cycles":"104306358",
          "real_time_nsec":"40190858",
          "PAPI_L2_DCM":"36336"
        },
        "71":{
          "name":"bcast",
          "parent_region_id":"-1",
          "cycles":"56761458",
          "real_time_nsec":"21868838",
          "PAPI_L2_DCM":"263644"
        },
        "72":{
          "name":"v0",
          "parent_region_id":"-1",
          "cycles":"356194072",
          "real_time_nsec":"137254134",
          "PAPI_L2_DCM":"486573"
        },
        "73":{
          "name":"isend",
          "parent_region_id":"-1",
          "cycles":"61766042",
          "real_time_nsec":"23795414",
          "PAPI_L2_DCM":"16230"
        },
        "74":{
          "name":"onesided",
          "parent_region_id":"-1",
          "cycles":"105242358",
          "real_time_nsec":"40553539",
          "PAPI_L2_DCM":"29283"
        },
        "75":{
          "name":"bcast",
          "parent_region_id":"-1",
          "cycles":"57883774",
          "real_time_nsec":"22301550",
          "PAPI_L2_DCM":"261986"
        },
        "76":{
          "name":"v0",
          "parent_region_id":"-1",
          "cycles":"372003424",
          "real_time_nsec":"143345619",
          "PAPI_L2_DCM":"473327"
        },
        "77":{
          "name":"isend",
          "parent_region_id":"-1",
          "cycles":"61770488",
          "real_time_nsec":"23797278",
          "PAPI_L2_DCM":"17483"
        },
        "78":{
          "name":"onesided",
          "parent_region_id":"-1",
          "cycles":"106394080",
          "real_time_nsec":"40992733",
          "PAPI_L2_DCM":"31764"
        },
        "79":{
          "name":"bcast",
          "parent_region_id":"-1",
          "cycles":"61240738",
          "real_time_nsec":"23595859",
          "PAPI_L2_DCM":"258754"
        }
      }
    }
  }
}
