{
  "papi_version":"7.0.1.0",
  "cpu_info":"AMD EPYC 7H12 64-Core Processor",
  "max_cpu_rate_mhz":"2600",
  "min_cpu_rate_mhz":"1500",
  "event_definitions":{
    "PAPI_L2_DCM":{
      "component":"perf_event",
      "type":"delta"
    }
  },
  "threads":{
    "0":{
      "regions":{
        "0":{
          "name":"computation",
          "parent_region_id":"-1",
          "cycles":"72964424",
          "real_time_nsec":"28115735",
          "PAPI_L2_DCM":"59314"
        },
        "1":{
          "name":"computation",
          "parent_region_id":"-1",
          "cycles":"71894264",
          "real_time_nsec":"27698785",
          "PAPI_L2_DCM":"58807"
        },
        "2":{
          "name":"computation",
          "parent_region_id":"-1",
          "cycles":"72446374",
          "real_time_nsec":"27909229",
          "PAPI_L2_DCM":"57204"
        },
        "3":{
          "name":"computation",
          "parent_region_id":"-1",
          "cycles":"72834918",
          "real_time_nsec":"28062476",
          "PAPI_L2_DCM":"58183"
        },
        "4":{
          "name":"computation",
          "parent_region_id":"-1",
          "cycles":"72940582",
          "real_time_nsec":"28104204",
          "PAPI_L2_DCM":"60265"
        },
        "5":{
          "name":"computation",
          "parent_region_id":"-1",
          "cycles":"72282730",
          "real_time_nsec":"27849567",
          "PAPI_L2_DCM":"62211"
        },
        "6":{
          "name":"computation",
          "parent_region_id":"-1",
          "cycles":"78633230",
          "real_time_nsec":"30297152",
          "PAPI_L2_DCM":"52868"
        },
        "7":{
          "name":"computation",
          "parent_region_id":"-1",
          "cycles":"73424208",
          "real_time_nsec":"28291886",
          "PAPI_L2_DCM":"52262"
        },
        "8":{
          "name":"computation",
          "parent_region_id":"-1",
          "cycles":"72042152",
          "real_time_nsec":"27728580",
          "PAPI_L2_DCM":"56866"
        },
        "9":{
          "name":"computation",
          "parent_region_id":"-1",
          "cycles":"93395224",
          "real_time_nsec":"35986422",
          "PAPI_L2_DCM":"63937"
        },
        "10":{
          "name":"computation",
          "parent_region_id":"-1",
          "cycles":"73679892",
          "real_time_nsec":"28385933",
          "PAPI_L2_DCM":"59549"
        },
        "11":{
          "name":"computation",
          "parent_region_id":"-1",
          "cycles":"92125514",
          "real_time_nsec":"35495051",
          "PAPI_L2_DCM":"55439"
        },
        "12":{
          "name":"computation",
          "parent_region_id":"-1",
          "cycles":"86386248",
          "real_time_nsec":"33288197",
          "PAPI_L2_DCM":"53637"
        },
        "13":{
          "name":"computation",
          "parent_region_id":"-1",
          "cycles":"72669948",
          "real_time_nsec":"27997023",
          "PAPI_L2_DCM":"57111"
        },
        "14":{
          "name":"computation",
          "parent_region_id":"-1",
          "cycles":"76518806",
          "real_time_nsec":"29487496",
          "PAPI_L2_DCM":"58840"
        },
        "15":{
          "name":"computation",
          "parent_region_id":"-1",
          "cycles":"73259160",
          "real_time_nsec":"28226373",
          "PAPI_L2_DCM":"57526"
        },
        "16":{
          "name":"computation",
          "parent_region_id":"-1",
          "cycles":"75505352",
          "real_time_nsec":"29097115",
          "PAPI_L2_DCM":"58030"
        },
        "17":{
          "name":"computation",
          "parent_region_id":"-1",
          "cycles":"73695830",
          "real_time_nsec":"28394819",
          "PAPI_L2_DCM":"59231"
        },
        "18":{
          "name":"computation",
          "parent_region_id":"-1",
          "cycles":"74833746",
          "real_time_nsec":"28832650",
          "PAPI_L2_DCM":"55414"
        },
        "19":{
          "name":"computation",
          "parent_region_id":"-1",
          "cycles":"75551398",
          "real_time_nsec":"29109458",
          "PAPI_L2_DCM":"57837"
        }
      }
    }
  }
}
