{
  "papi_version":"7.0.1.0",
  "cpu_info":"AMD EPYC 7H12 64-Core Processor",
  "max_cpu_rate_mhz":"2600",
  "min_cpu_rate_mhz":"1500",
  "event_definitions":{
    "PAPI_L2_DCM":{
      "component":"perf_event",
      "type":"delta"
    }
  },
  "threads":{
    "0":{
      "regions":{
        "0":{
          "name":"computation",
          "parent_region_id":"-1",
          "cycles":"71360562",
          "real_time_nsec":"27492527",
          "PAPI_L2_DCM":"58791"
        },
        "1":{
          "name":"computation",
          "parent_region_id":"-1",
          "cycles":"71886334",
          "real_time_nsec":"27697522",
          "PAPI_L2_DCM":"54525"
        },
        "2":{
          "name":"computation",
          "parent_region_id":"-1",
          "cycles":"72434284",
          "real_time_nsec":"27909279",
          "PAPI_L2_DCM":"56393"
        },
        "3":{
          "name":"computation",
          "parent_region_id":"-1",
          "cycles":"72812922",
          "real_time_nsec":"28056003",
          "PAPI_L2_DCM":"59480"
        },
        "4":{
          "name":"computation",
          "parent_region_id":"-1",
          "cycles":"72935850",
          "real_time_nsec":"28103272",
          "PAPI_L2_DCM":"54629"
        },
        "5":{
          "name":"computation",
          "parent_region_id":"-1",
          "cycles":"72273812",
          "real_time_nsec":"27847853",
          "PAPI_L2_DCM":"58970"
        },
        "6":{
          "name":"computation",
          "parent_region_id":"-1",
          "cycles":"78638560",
          "real_time_nsec":"30301751",
          "PAPI_L2_DCM":"57213"
        },
        "7":{
          "name":"computation",
          "parent_region_id":"-1",
          "cycles":"73429382",
          "real_time_nsec":"28294360",
          "PAPI_L2_DCM":"60228"
        },
        "8":{
          "name":"computation",
          "parent_region_id":"-1",
          "cycles":"72468240",
          "real_time_nsec":"27922404",
          "PAPI_L2_DCM":"56042"
        },
        "9":{
          "name":"computation",
          "parent_region_id":"-1",
          "cycles":"93559388",
          "real_time_nsec":"36050593",
          "PAPI_L2_DCM":"58379"
        },
        "10":{
          "name":"computation",
          "parent_region_id":"-1",
          "cycles":"73464820",
          "real_time_nsec":"28310371",
          "PAPI_L2_DCM":"56122"
        },
        "11":{
          "name":"computation",
          "parent_region_id":"-1",
          "cycles":"91973050",
          "real_time_nsec":"35446461",
          "PAPI_L2_DCM":"56343"
        },
        "12":{
          "name":"computation",
          "parent_region_id":"-1",
          "cycles":"86643830",
          "real_time_nsec":"33392081",
          "PAPI_L2_DCM":"61932"
        },
        "13":{
          "name":"computation",
          "parent_region_id":"-1",
          "cycles":"72689812",
          "real_time_nsec":"28005760",
          "PAPI_L2_DCM":"60416"
        },
        "14":{
          "name":"computation",
          "parent_region_id":"-1",
          "cycles":"76537006",
          "real_time_nsec":"29490051",
          "PAPI_L2_DCM":"53476"
        },
        "15":{
          "name":"computation",
          "parent_region_id":"-1",
          "cycles":"73265712",
          "real_time_nsec":"28230391",
          "PAPI_L2_DCM":"55607"
        },
        "16":{
          "name":"computation",
          "parent_region_id":"-1",
          "cycles":"75166078",
          "real_time_nsec":"28966290",
          "PAPI_L2_DCM":"57155"
        },
        "17":{
          "name":"computation",
          "parent_region_id":"-1",
          "cycles":"73728850",
          "real_time_nsec":"28409898",
          "PAPI_L2_DCM":"53818"
        },
        "18":{
          "name":"computation",
          "parent_region_id":"-1",
          "cycles":"74831978",
          "real_time_nsec":"28834162",
          "PAPI_L2_DCM":"68131"
        },
        "19":{
          "name":"computation",
          "parent_region_id":"-1",
          "cycles":"75257208",
          "real_time_nsec":"29002228",
          "PAPI_L2_DCM":"53506"
        }
      }
    }
  }
}
